graphql_explorer/__init__.py
graphql_explorer/fastapi.py
graphql_explorer/templates/__init__.py
graphql_explorer/templates/apollo_sandbox.py
graphql_explorer/templates/graphiql.py
graphql_explorer/templates/pathfinder.py
graphql_explorer/templates/voyager.py
graphql_explorer-0.1.4.dist-info/METADATA
graphql_explorer-0.1.4.dist-info/WHEEL
graphql_explorer-0.1.4.dist-info/RECORD
