Metadata-Version: 2.1
Name: graphql-explorer
Version: 0.1.4
Summary: 
Author: Abhinand C
Author-email: abhinandc.ac@gmail.com
Requires-Python: >=3.7
Classifier: Programming Language :: Python :: 3
Classifier: Programming Language :: Python :: 3.7
Classifier: Programming Language :: Python :: 3.8
Classifier: Programming Language :: Python :: 3.9
Classifier: Programming Language :: Python :: 3.10
Classifier: Programming Language :: Python :: 3.11
